modulehooks.py
modulehooks-1.0.0.dist-info/LICENSE
modulehooks-1.0.0.dist-info/METADATA
modulehooks-1.0.0.dist-info/WHEEL
modulehooks-1.0.0.dist-info/top_level.txt
modulehooks-1.0.0.dist-info/RECORD
