Metadata-Version: 2.1
Name: modulehooks
Version: 1.0.0
Summary: Wrapping modules with attribute hooks
Home-page: https://github.com/rayzchen/modulehooks
Author: Ray Chen
Author-email: tankimarshal2@gmail.com
License: UNKNOWN
Platform: UNKNOWN
Classifier: Development Status :: 5 - Production/Stable
Classifier: Natural Language :: English
Classifier: License :: OSI Approved :: MIT License
Classifier: Intended Audience :: Developers
Classifier: Natural Language :: English
Classifier: Programming Language :: Python :: 3
Requires-Python: >=3.6
License-File: LICENSE
